funky_fortune/__init__.py
funky_fortune/main.py
funky_fortune-0.1.0.dist-info/LICENSE
funky_fortune-0.1.0.dist-info/METADATA
funky_fortune-0.1.0.dist-info/WHEEL
funky_fortune-0.1.0.dist-info/top_level.txt
funky_fortune-0.1.0.dist-info/RECORD
