Metadata-Version: 2.1
Name: funky_fortune
Version: 0.1.0
Summary: Divination Python package
Author: Bug Creators
License: GNU GENERAL PUBLIC LICENSE
Project-URL: Repository, https://github.com/software-students-fall2024/3-python-package-bug-creator-v3
Project-URL: Bug Tracker, https://github.com/software-students-fall2024/3-python-package-bug-creator-v3/issues
Keywords: python,package,build,fortune,lucky
Classifier: Programming Language :: Python :: 3
Classifier: Intended Audience :: Education
Classifier: License :: OSI Approved :: GNU General Public License v3 (GPLv3)
Classifier: Operating System :: OS Independent
Requires-Python: >=3.7
License-File: LICENSE
Provides-Extra: dev
Requires-Dist: pytest; extra == "dev"
